README.md
setup.py
fdbk_mongodb_plugin/__init__.py
fdbk_mongodb_plugin/_mongodb_connection.py
fdbk_mongodb_plugin/_version.py
fdbk_mongodb_plugin.egg-info/PKG-INFO
fdbk_mongodb_plugin.egg-info/SOURCES.txt
fdbk_mongodb_plugin.egg-info/dependency_links.txt
fdbk_mongodb_plugin.egg-info/requires.txt
fdbk_mongodb_plugin.egg-info/top_level.txt